AUTHORS.rst
HISTORY.rst
LICENSE
MANIFEST.in
README.rst
setup.py
dgit_extensions/__init__.py
dgit_extensions.egg-info/PKG-INFO
dgit_extensions.egg-info/SOURCES.txt
dgit_extensions.egg-info/dependency_links.txt
dgit_extensions.egg-info/entry_points.txt
dgit_extensions.egg-info/not-zip-safe
dgit_extensions.egg-info/requires.txt
dgit_extensions.egg-info/top_level.txt
dgit_extensions/generators/__init__.py
dgit_extensions/generators/mysql_generator.py
dgit_extensions/security/__init__.py
dgit_extensions/security/simple_file_encryptor.py
dgit_extensions/security/simple_table_anonymizer.py