Metadata-Version: 1.1
Name: dgit-extensions
Version: 0.1.3
Summary: dgit addons
Home-page: http://github.com/pingali/dgit-extensions
Author: Venkata Pingali
Author-email: pingali@gmail.com
License: MIT
Keywords: dgit dataset versioning addons
Platform: UNKNOWN
Classifier: Development Status :: 3 - Alpha
Classifier: Intended Audience :: Developers
Classifier: Natural Language :: English
Classifier: License :: OSI Approved :: MIT License
Classifier: Programming Language :: Python :: 3 :: Only
Classifier: Topic :: Scientific/Engineering :: Information Analysis
